Workbook

Sheet Assumptions
A1: 雙鍵化工(4764) 估值模型 — 輸入假設(藍字可改,全表連動)
A2: 校準基準:26Q2月營收加總932.9(對方模型預實誤差-2.0%綠燈);現價236.5(2026/7/30);股數0.855億
A4: 現價(元) | B4: 236.5
A5: 稅率 | B5: 0.2
A6: 流通股數(億股) | B6: 0.855
A7: CB潛在稀釋(億股) ※CB 5億,依轉換價概估 | B7: 0.017
A8: 稀釋後股數(億股) | B8: =B6+B7
A9: 傳統材料營收/季(百萬) ※塑膠添加劑+光固化,模型假設平盤 | B9: 560
A10: 傳統材料毛利率 | B10: 0.14
A11: 電子樹脂毛利率 2026H2 ※1Q26反推約53%,保守給 | B11: 0.44
A12: 電子樹脂毛利率 2027 ※HC占比升+良率爬坡 | B12: 0.48
A13: 營業費用率 2026H2 | B13: 0.09
A14: 營業費用率 2027 ※營收放大攤薄(對方模型隱含~7.3%) | B14: 0.075
A15: 業外損益/季(百萬) ※財務成本,CB到位償還11.1億借款後改善 | B15: -8
A16: 1H26 已實現EPS(自結) | B16: 2.25
A18: 季度營運假設(核心兩顆鈕:月出貨噸數 × 樹脂ASP)
A19: 季度 | C19: 26Q3E | D19: 26Q4E | E19: 27Q1E | F19: 27Q2E | G19: 27Q3E | H19: 27Q4E
A20: 月出貨噸數(噸/月) | C20: 160 | D20: 235 | E20: 350 | F20: 360 | G20: 370 | H20: 370
A21: 樹脂ASP(NTD/KG) | C21: 1325 | D21: 1550 | E21: 1670 | F21: 1660 | G21: 1650 | H21: 1650
A23: 假設依據(法說+供應鏈筆記):目前90-110噸/月→4Q26目標220-250噸/月;宜蘭產能上修遠超2,000噸/年;
A24: ASP:BMI 500-600→FY25已達900-1,000(mPPO出貨實績)→M7/M8放量mPPO為主劑、M8起摻HC(單價最高)→ASP階梯上行;
A25: 26Q3校準:160噸×1,325≈636百萬=對方模型Q3E 1,223×電子占比52%。27年:350噸×1,670≈對方27Q電子~1,754。

Sheet Model
A1: 季度損益模型(百萬) — 電子=噸×3×ASP/1000;藍色實績、其餘公式連動
A3: 季度 | B3: 26Q1A | C3: 26Q2A | D3: 26Q3E | E3: 26Q4E | F3: 27Q1E | G3: 27Q2E | H3: 27Q3E | I3: 27Q4E
A4: 電子樹脂營收 | B4: 272 | C4: 392 | D4: =Assumptions!C20*3*Assumptions!C21/1000 | E4: =Assumptions!D20*3*Assumptions!D21/1000 | F4: =Assumptions!E20*3*Assumptions!E21/1000 | G4: =Assumptions!F20*3*Assumptions!F21/1000 | H4: =Assumptions!G20*3*Assumptions!G21/1000 | I4: =Assumptions!H20*3*Assumptions!H21/1000
A5: 傳統材料營收 | B5: 551 | C5: 541 | D5: =Assumptions!$B$9 | E5: =Assumptions!$B$9 | F5: =Assumptions!$B$9 | G5: =Assumptions!$B$9 | H5: =Assumptions!$B$9 | I5: =Assumptions!$B$9
A6: 總營收 | B6: 823 | C6: 933 | D6: =D4+D5 | E6: =E4+E5 | F6: =F4+F5 | G6: =G4+G5 | H6: =H4+H5 | I6: =I4+I5
A7: 電子占比 | D7: =D4/D6 | E7: =E4/E6 | F7: =F4/F6 | G7: =G4/G6 | H7: =H4/H6 | I7: =I4/I6
A8: 毛利率(blended) | B8: =B6*B9 | D8: =D7*Assumptions!$B$11+(1-D7)*Assumptions!$B$10 | E8: =E7*Assumptions!$B$11+(1-E7)*Assumptions!$B$10 | F8: =F7*Assumptions!$B$12+(1-F7)*Assumptions!$B$10 | G8: =G7*Assumptions!$B$12+(1-G7)*Assumptions!$B$10 | H8: =H7*Assumptions!$B$12+(1-H7)*Assumptions!$B$10 | I8: =I7*Assumptions!$B$12+(1-I7)*Assumptions!$B$10
A9: (同上) | B9: 0.2653 | D9: =D8 | E9: =E8 | F9: =F8 | G9: =G8 | H9: =H8 | I9: =I8
A10: 毛利 | D10: =D6*D8 | E10: =E6*E8 | F10: =F6*F8 | G10: =G6*G8 | H10: =H6*H8 | I10: =I6*I8
A11: 營業費用 | B11: 121 | D11: =D6*Assumptions!$B$13 | E11: =E6*Assumptions!$B$13 | F11: =F6*Assumptions!$B$14 | G11: =G6*Assumptions!$B$14 | H11: =H6*Assumptions!$B$14 | I11: =I6*Assumptions!$B$14
A12: 營業利益 | D12: =D10-D11 | E12: =E10-E11 | F12: =F10-F11 | G12: =G10-G11 | H12: =H10-H11 | I12: =I10-I11
A13: 營益率 | D13: =D12/D6 | E13: =E12/E6 | F13: =F12/F6 | G13: =G12/G6 | H13: =H12/H6 | I13: =I12/I6
A14: 業外 | B14: 88 | D14: =Assumptions!$B$15 | E14: =Assumptions!$B$15 | F14: =Assumptions!$B$15 | G14: =Assumptions!$B$15 | H14: =Assumptions!$B$15 | I14: =Assumptions!$B$15
A15: 稅前 | D15: =D12+D14 | E15: =E12+E14 | F15: =F12+F14 | G15: =G12+G14 | H15: =H12+H14 | I15: =I12+I14
A16: 稅後淨利 | B16: 1.03 | C16: 1.22 | D16: =D15*(1-Assumptions!$B$5) | E16: =E15*(1-Assumptions!$B$5) | F16: =F15*(1-Assumptions!$B$5) | G16: =G15*(1-Assumptions!$B$5) | H16: =H15*(1-Assumptions!$B$5) | I16: =I15*(1-Assumptions!$B$5)
A17: EPS(元) | D17: =D16/(Assumptions!$B$8*100) | E17: =E16/(Assumptions!$B$8*100) | F17: =F16/(Assumptions!$B$8*100) | G17: =G16/(Assumptions!$B$8*100) | H17: =H16/(Assumptions!$B$8*100) | I17: =I16/(Assumptions!$B$8*100)
A19: FY26 EPS(1H實績2.25+2H推估) | B19: =Assumptions!$B$16+D17+E17
A20: FY27 EPS(四季推估) | B20: =F17+G17+H17+I17
A22: 對方模型軌跡(對照):26Q3E 1,223→26Q4E 1,684→27年單季~2,370-2,382;毛利率26.5%→39.4%;營益率14.7%→32.1%
A23: 預實紀錄:26Q2 模型951.6 vs 實際933 誤差-2.0%(±5%內綠燈)。下一驗證:7月營收(8/10公布)月均應~408

Sheet Valuation
A1: 估值 — FY27E EPS × 本益比情境
A3: FY27E EPS(連動Model) | B3: =Model!B20
A4: FY26E EPS | B4: =Model!B19
A5: 現價 | B5: =Assumptions!B4
A7: 本益比 | B7: 目標價(FY27E) | C7: vs現價
A8: 17 | B8: =$B$3*A8 | C8: =B8/$B$5-1
A9: 20 | B9: =$B$3*A9 | C9: =B9/$B$5-1
A10: 25 | B10: =$B$3*A10 | C10: =B10/$B$5-1
A11: 30 | B11: =$B$3*A11 | C11: =B11/$B$5-1
A12: 35 | B12: =$B$3*A12 | C12: =B12/$B$5-1
A14: 敏感度:FY27 EPS = f(27年月噸數, 27年ASP) ※毛利率/費用率沿用 Assumptions
A15: ASP\噸/月 | B15: 300 | C15: 350 | D15: 400 | E15: 430
A16: 1500 | B16: =4*(((300*3*1500/1000+Assumptions!$B$9)*((300*3*1500/1000)/(300*3*1500/1000+Assumptions!$B$9)*Assumptions!$B$12+(1-(300*3*1500/1000)/(300*3*1500/1000+Assumptions!$B$9))*Assumptions!$B$10)-(300*3*1500/1000+Assumptions!$B$9)*Assumptions!$B$14+Assumptions!$B$15)*(1-Assumptions!$B$5))/(Assumptions!$B$8*100) | C16: =4*(((350*3*1500/1000+Assumptions!$B$9)*((350*3*1500/1000)/(350*3*1500/1000+Assumptions!$B$9)*Assumptions!$B$12+(1-(350*3*1500/1000)/(350*3*1500/1000+Assumptions!$B$9))*Assumptions!$B$10)-(350*3*1500/1000+Assumptions!$B$9)*Assumptions!$B$14+Assumptions!$B$15)*(1-Assumptions!$B$5))/(Assumptions!$B$8*100) | D16: =4*(((400*3*1500/1000+Assumptions!$B$9)*((400*3*1500/1000)/(400*3*1500/1000+Assumptions!$B$9)*Assumptions!$B$12+(1-(400*3*1500/1000)/(400*3*1500/1000+Assumptions!$B$9))*Assumptions!$B$10)-(400*3*1500/1000+Assumptions!$B$9)*Assumptions!$B$14+Assumptions!$B$15)*(1-Assumptions!$B$5))/(Assumptions!$B$8*100) | E16: =4*(((430*3*1500/1000+Assumptions!$B$9)*((430*3*1500/1000)/(430*3*1500/1000+Assumptions!$B$9)*Assumptions!$B$12+(1-(430*3*1500/1000)/(430*3*1500/1000+Assumptions!$B$9))*Assumptions!$B$10)-(430*3*1500/1000+Assumptions!$B$9)*Assumptions!$B$14+Assumptions!$B$15)*(1-Assumptions!$B$5))/(Assumptions!$B$8*100)
A17: 1650 | B17: =4*(((300*3*1650/1000+Assumptions!$B$9)*((300*3*1650/1000)/(300*3*1650/1000+Assumptions!$B$9)*Assumptions!$B$12+(1-(300*3*1650/1000)/(300*3*1650/1000+Assumptions!$B$9))*Assumptions!$B$10)-(300*3*1650/1000+Assumptions!$B$9)*Assumptions!$B$14+Assumptions!$B$15)*(1-Assumptions!$B$5))/(Assumptions!$B$8*100) | C17: =4*(((350*3*1650/1000+Assumptions!$B$9)*((350*3*1650/1000)/(350*3*1650/1000+Assumptions!$B$9)*Assumptions!$B$12+(1-(350*3*1650/1000)/(350*3*1650/1000+Assumptions!$B$9))*Assumptions!$B$10)-(350*3*1650/1000+Assumptions!$B$9)*Assumptions!$B$14+Assumptions!$B$15)*(1-Assumptions!$B$5))/(Assumptions!$B$8*100) | D17: =4*(((400*3*1650/1000+Assumptions!$B$9)*((400*3*1650/1000)/(400*3*1650/1000+Assumptions!$B$9)*Assumptions!$B$12+(1-(400*3*1650/1000)/(400*3*1650/1000+Assumptions!$B$9))*Assumptions!$B$10)-(400*3*1650/1000+Assumptions!$B$9)*Assumptions!$B$14+Assumptions!$B$15)*(1-Assumptions!$B$5))/(Assumptions!$B$8*100) | E17: =4*(((430*3*1650/1000+Assumptions!$B$9)*((430*3*1650/1000)/(430*3*1650/1000+Assumptions!$B$9)*Assumptions!$B$12+(1-(430*3*1650/1000)/(430*3*1650/1000+Assumptions!$B$9))*Assumptions!$B$10)-(430*3*1650/1000+Assumptions!$B$9)*Assumptions!$B$14+Assumptions!$B$15)*(1-Assumptions!$B$5))/(Assumptions!$B$8*100)
A18: 1800 | B18: =4*(((300*3*1800/1000+Assumptions!$B$9)*((300*3*1800/1000)/(300*3*1800/1000+Assumptions!$B$9)*Assumptions!$B$12+(1-(300*3*1800/1000)/(300*3*1800/1000+Assumptions!$B$9))*Assumptions!$B$10)-(300*3*1800/1000+Assumptions!$B$9)*Assumptions!$B$14+Assumptions!$B$15)*(1-Assumptions!$B$5))/(Assumptions!$B$8*100) | C18: =4*(((350*3*1800/1000+Assumptions!$B$9)*((350*3*1800/1000)/(350*3*1800/1000+Assumptions!$B$9)*Assumptions!$B$12+(1-(350*3*1800/1000)/(350*3*1800/1000+Assumptions!$B$9))*Assumptions!$B$10)-(350*3*1800/1000+Assumptions!$B$9)*Assumptions!$B$14+Assumptions!$B$15)*(1-Assumptions!$B$5))/(Assumptions!$B$8*100) | D18: =4*(((400*3*1800/1000+Assumptions!$B$9)*((400*3*1800/1000)/(400*3*1800/1000+Assumptions!$B$9)*Assumptions!$B$12+(1-(400*3*1800/1000)/(400*3*1800/1000+Assumptions!$B$9))*Assumptions!$B$10)-(400*3*1800/1000+Assumptions!$B$9)*Assumptions!$B$14+Assumptions!$B$15)*(1-Assumptions!$B$5))/(Assumptions!$B$8*100) | E18: =4*(((430*3*1800/1000+Assumptions!$B$9)*((430*3*1800/1000)/(430*3*1800/1000+Assumptions!$B$9)*Assumptions!$B$12+(1-(430*3*1800/1000)/(430*3*1800/1000+Assumptions!$B$9))*Assumptions!$B$10)-(430*3*1800/1000+Assumptions!$B$9)*Assumptions!$B$14+Assumptions!$B$15)*(1-Assumptions!$B$5))/(Assumptions!$B$8*100)
A20: 讀法:對方模型27年隱含約370噸×1,650 → 看該格EPS×你願給的本益比,即目標價;
A21: 現價236.5要合理,需要哪一格×幾倍本益比,自己對照——這就是「市場定價隱含的假設」。

Sheet Notes
A1: 供應鏈競局・配方階梯・追蹤點・風險
A3: ■ CCL樹脂供應鏈四角色(供應鏈筆記):
A4: 三菱瓦斯|技術原創者/定價者,OPE標竿垂直整合到板材,不擴量只提價 → 定價傘,給了追隨者空間
A5: JSR |配方IP擁有者,製造外包國精化,輕資產抽價值鏈80%
A6: 國精化 |受託製造平台,賺代工費
A7: 雙鍵 |完全自產自銷 → 實質瓶頸=產能開出速度+良率爬坡;關注樹脂ASP與出貨噸數逐步增加
A9: ■ 配方階梯(單價由低到高):BMI(副劑,管Tg/CTE,拉高Df)→ mPPO(主劑,管Dk,後續升級核心)
A10: → OPE(改質mPPO)→ HC(零極性,耐熱差但單價最高)。M7/M8:mPPO主劑;M8起摻HC;M9拉升HC比例
A11: 設備:mPPO/HC可調校轉換,BMI設備無法沿用 → 宜蘭新產能應瞄準mPPO以上及HC
A13: ■ 宜蘭廠:原光固化擴建轉電子化學品,產能目標2,000噸/年→已上修遠超;錢2023年前花完、折舊已列
A14: → 現在是「收割產能利用率」階段(折舊平台~42.6/季,營收放大=營益率跳升的結構基礎)
A16: ■ 資金:7月CB 5億(純CB,現增暫緩);到位償還11.1億借款 → 利息負擔下降;2025營業現金流281 vs 淨利107品質佳
... A29: 5. 股價已從低點大漲後回檔35%,1H26 EPS 2.25對現價236.5=年化~52倍,價格已含高成長預期
